{
    "info": {
        "time": "true",
        "date": "true",
        "duration": "true",
        "id": "true"
    },
    "read_data": {
        "saved": "true",
        "gray": "true",
        "new_size": "true",
        "normalize": "true",
        "transpose": "true"
    },
    "apply_glcm": {
        "distance": "true"
    },
    "SVC": {
        "kernel": "true",
        "C": "true",
        "degree": "true",
        "gamma": "true",
        "coef0": "true",
        "shrinking": "true",
        "probability": "true",
        "tol": "true",
        "cache_size": "true",
        "verbose": "true",
        "max_iter": "true",
        "decision_function_shape": "true",
        "break_ties": "true"
    },
    "metrics": {
        "Accuracy": "true",
        "F1": "true"
    }
}